private_sdk/__init__.py
private_sdk/__main__.py
private_sdk/client.py
private_sdk/constants.py
private_sdk/error.py
private_sdk/http.py
private_sdk/models.py
private_sdk/signature.py
private_sdk/utils.py
private_sdk/version.py
bge_private_sdk-0.1a1.dist-info/LICENSE
bge_private_sdk-0.1a1.dist-info/METADATA
bge_private_sdk-0.1a1.dist-info/WHEEL
bge_private_sdk-0.1a1.dist-info/entry_points.txt
bge_private_sdk-0.1a1.dist-info/top_level.txt
bge_private_sdk-0.1a1.dist-info/RECORD
