Metadata-Version: 2.1
Name: bge-private-sdk
Version: 0.1a1
Summary: 可用于调用 BGE 私有平台的相关接口。
Home-page: https://github.com/teambge/bge-private-sdk.git
Author: leafcoder,xiangji1204
Author-email: leafcoder@gmail.com,xiangji@genomics.cn
License: MIT
Keywords: bge-private-sdk bge private_sdk private
Platform: UNKNOWN
Classifier: Development Status :: 5 - Production/Stable
Classifier: Intended Audience :: Developers
Classifier: License :: OSI Approved :: MIT License
Classifier: Natural Language :: Chinese (Simplified)
Classifier: Operating System :: OS Independent
Classifier: Programming Language :: Python
Classifier: Programming Language :: Python :: 2.7
Classifier: Programming Language :: Python :: 3
Classifier: Programming Language :: Python :: 3.5
Classifier: Programming Language :: Python :: 3.6
Classifier: Programming Language :: Python :: 3.7
Classifier: Topic :: Software Development :: Libraries
Classifier: Topic :: Software Development :: Libraries :: Python Modules
Classifier: Topic :: Utilities
License-File: LICENSE
Requires-Dist: requests
Requires-Dist: urllib3
Requires-Dist: six
